django_payments_paybox/__init__.py
django_payments_paybox/provider.py
django_payments_paybox/schemas.py
django_payments_paybox/utils.py
django_payments_paybox-0.2.3.dist-info/LICENSE
django_payments_paybox-0.2.3.dist-info/WHEEL
django_payments_paybox-0.2.3.dist-info/METADATA
django_payments_paybox-0.2.3.dist-info/RECORD
