Metadata-Version: 2.1
Name: django-payments-paybox
Version: 0.2.3
Summary: django-payments provider for PayBox.money
Home-page: https://github.com/vlzh/django-payments-paybox
Author: vlzh
Author-email: vlzh@pm.me
Requires-Python: >=3.6,<4.0
Classifier: Programming Language :: Python :: 3
Classifier: Programming Language :: Python :: 3.6
Classifier: Programming Language :: Python :: 3.7
Classifier: Programming Language :: Python :: 3.8
Requires-Dist: pydantic (>=1.6.1,<2.0.0)
Project-URL: Repository, https://github.com/vlzh/django-payments-paybox
